vsom/__init__.py
vsom/fine_tuning.py
vsom/fine_tuning_HypOpmit.py
vsom/predict_evalute_draw.py
vsom/pretraining.py
vsom/vocab.txt
vsom-0.1.7.dist-info/LICENSE.txt
vsom-0.1.7.dist-info/WHEEL
vsom-0.1.7.dist-info/METADATA
vsom-0.1.7.dist-info/RECORD
