Metadata-Version: 2.1
Name: vsom
Version: 0.1.7
Summary: the code of virtual screening of organic materials
License: MIT
Author: su-group
Requires-Python: >=3.6,<4.0
Classifier: License :: OSI Approved :: MIT License
Classifier: Programming Language :: Python :: 3
Classifier: Programming Language :: Python :: 3.10
Classifier: Programming Language :: Python :: 3.6
Classifier: Programming Language :: Python :: 3.7
Classifier: Programming Language :: Python :: 3.8
Classifier: Programming Language :: Python :: 3.9
Requires-Dist: matplotlib (>=3.9.1,<4.0.0)
Requires-Dist: numpy (>=1.19.2,<2.0)
Requires-Dist: pandas (>=1.1.5,<2.0)
Requires-Dist: rdkit (>=2023.9.1,<2024.0.0)
Requires-Dist: seaborn (>=0.13.2,<0.14.0)
